{
  "character_name": "姫島朱乃",
  "char_id": "",
  "source": "local",
  "moan": {
    "1": [
      "あふ…",
      "んぅっ…",
      "んはぁ…",
      "んはっ",
      "んくっ…",
      "んぅん…",
      "んっ…",
      "んっ…っ"
    ],
    "2": [
      "んんっ♡",
      "あふぅ…♡",
      "あやっ♡",
      "んふあっ♡",
      "あっ♡",
      "あぁ…",
      "んにゃっ♡",
      "んあんっ…"
    ],
    "3": [
      "あぁんっ♡♡",
      "んはぁっ♡",
      "んほぅ…♡♡",
      "んあぁっ♡♡",
      "んあはっ♡♡",
      "んあやっ♡♡",
      "あはぁっ♡♡",
      "んあっ♡♡"
    ],
    "4": [
      "あ゛ぁぁ♡♡",
      "あ゛ぁっ♡♡",
      "あ゛やっ♡♡",
      "ん゛やっ♡♡",
      "あ゛くっ♡♡",
      "ん゛おぉっ♡♡",
      "あ゛っ♡♡",
      "んほぉんっ♡♡"
    ],
    "5": [
      "あ゛あ゛ひっ♡♡♡",
      "いぐっ♡♡♡",
      "いぐんっ♡♡♡",
      "あ゛あ゛ふっ♡♡♡",
      "あへぇんっ♡♡♡",
      "あへぇぇっ♡♡♡",
      "いぐぅんっ♡♡♡",
      "いぐぅぁっ♡♡♡"
    ]
  },
  "speech": {
    "intro": [
      "ここ…触ってほしいの…♡",
      "弱いなぁ♡",
      "なに見てるの",
      "まだ…入れちゃだめ…♡",
      "まだまだ♡"
    ],
    "approach": [
      "ここ…濡れてるの…わかる…？",
      "かかってきて",
      "先っぽだけ…♡",
      "こわいかしら…",
      "もう固くなってる…♡"
    ],
    "foreplay": [
      "見すぎ…",
      "まって…♡",
      "逃げないで♡",
      "ほらもっと♡",
      "こんなの…初めて…"
    ],
    "penetration": [
      "そこ…いい♡",
      "いたっ…♡",
      "あっ…動かないで…",
      "もうだめぇ♡",
      "ちょうだい♡"
    ],
    "climax": [
      "奥でイく♡♡",
      "すごいイく♡",
      "ぶっとぶ…♡",
      "キスして…♡",
      "全部ちょうだい"
    ],
    "afterglow": [
      "動けないわ…",
      "びっくりした",
      "もう…むりうふふ…",
      "夢じゃないよね…",
      "もう…無理…"
    ]
  },
  "thought": {
    "intro": [
      "とまんない…",
      "嘘でしょ…体が…",
      "体が勝手に…",
      "自分の声…信じれない",
      "変になる…"
    ],
    "approach": [
      "全身…びりびり",
      "ぴくぴくする…",
      "嘘でしょ…",
      "わからない…",
      "こんなので…イきそう"
    ],
    "foreplay": [
      "体が反応してる…",
      "嘘…感じてる…",
      "こんなの…初めて…",
      "力…入んない…",
      "声が…止まらない…"
    ],
    "penetration": [
      "もっと知りたい",
      "ゾクって…した…",
      "なにこれ…",
      "信じたくない…でも",
      "ぼやけて…る…"
    ],
    "climax": [
      "頭がくらくら",
      "お腹の奥が…",
      "イく…止まらない…♡",
      "ずっと…ずっと…",
      "立てない…"
    ],
    "afterglow": [
      "足の力が…",
      "ぞくぞくする…",
      "信じたくない…でも",
      "指が…震えて…",
      "変になる…"
    ]
  }
}