{
  "character_name": "カミラ",
  "char_id": "",
  "source": "local",
  "moan": {
    "1": [
      "んぅん…",
      "あふ…",
      "ん…っ",
      "んぅっ…",
      "んはぁ…",
      "んふっ…",
      "んくぅ…",
      "んはっ"
    ],
    "2": [
      "あっくっ…",
      "んやっ♡",
      "あんはっ♡",
      "んぅっ…♡",
      "んあんっ…",
      "あぁ…",
      "あんぅ…♡",
      "んはっ♡"
    ],
    "3": [
      "あんはっ♡♡",
      "あぁっ♡",
      "んはやっ♡♡",
      "んぁあっ♡♡",
      "んあはっ♡♡",
      "んはぁっ♡",
      "あへぅっ♡♡",
      "あへっ…♡♡"
    ],
    "4": [
      "ん゛あぁっ♡♡",
      "あ゛ぁっ♡♡",
      "ん゛ぁぁっ♡♡",
      "ん゛くっ♡♡",
      "あ゛やっ♡♡",
      "あへぇっ♡♡",
      "あ゛んっ♡♡",
      "あ゛ぁぁ♡♡"
    ],
    "5": [
      "あ゛あ゛ひっ♡♡♡",
      "あへぇっ♡♡♡",
      "んほっ♡♡♡",
      "あ゛あ゛おっ♡♡♡",
      "あへぇんっ♡♡♡",
      "あ゛あ゛はっ♡♡♡",
      "あ゛あ゛んっ♡♡♡",
      "あ゛あ゛あ゛ぁ♡♡♡"
    ]
  },
  "speech": {
    "intro": [
      "声…出ちゃう",
      "聞こえちゃう",
      "なに見てるの",
      "そこ…だめ…",
      "電気消して…"
    ],
    "approach": [
      "やだ…そんなの…",
      "やめてって…",
      "エッチ…",
      "音…やだ…",
      "むり…"
    ],
    "foreplay": [
      "そこ…だめわ…",
      "くすぐったい…",
      "感覚やばい…",
      "腰…もうかしら…",
      "え…もう…♡"
    ],
    "penetration": [
      "まって…大きい",
      "すき…♡",
      "奥に当たる♡",
      "お願いだから",
      "もっと…♡"
    ],
    "climax": [
      "溢れちゃう…♡♡",
      "止まんない♡",
      "ぶっとぶ…♡",
      "やば…イく♡",
      "もうだめ♡♡"
    ],
    "afterglow": [
      "…夢みたい…",
      "夢みたい…♡",
      "中…あついの…わかる…",
      "動けない…",
      "…抱きしめてよ…"
    ]
  },
  "thought": {
    "intro": [
      "なんか…へん…",
      "息ができない",
      "腰が…勝手に",
      "心臓…早い…",
      "なにこれ…"
    ],
    "approach": [
      "ここ…弱い…",
      "考えちゃだめ…感じちゃだめ…",
      "ふるえ…てる",
      "なんでこんな…",
      "理解できない…"
    ],
    "foreplay": [
      "熱くなってく…",
      "奥が…疼く…",
      "知らなかった…こんな",
      "信じたくない…でも",
      "力…入んない…"
    ],
    "penetration": [
      "こんなの初めて",
      "熱い…お腹の中…",
      "奥が…疼く…",
      "もっと欲しい…",
      "もう…だめかも…"
    ],
    "climax": [
      "意識が…",
      "もうだめかも",
      "指先が痺れて",
      "感じすぎ…",
      "体が…自分のじゃない…♡"
    ],
    "afterglow": [
      "…体が覚えちゃった…",
      "腰が…勝手に",
      "頭がぼーっと",
      "熱い…中が…",
      "思考が…飛ぶ"
    ]
  }
}